{"textures":{"0":"modelengine:entity/pet_angel"},"elements":[{"from":[6.911368,7.9870744,7.722725],"to":[12.054226,9.129931,8.33701],"rotation":{"angle":22.5,"axis":"z","origin":[9.1970825,9.70136,7.7370105]},"faces":{"east":{"uv":[10.75,0.0,10.5,0.5],"rotation":0,"texture":"#0","tintindex":0},"south":{"uv":[9.75,9.0,7.5,9.5],"rotation":0,"texture":"#0","tintindex":0},"north":{"uv":[7.25,8.75,5.0,9.25],"rotation":0,"texture":"#0","tintindex":0},"west":{"uv":[10.25,9.0,10.0,9.5],"rotation":0,"texture":"#0","tintindex":0},"up":{"uv":[9.0,10.0,11.25,9.75],"rotation":0,"texture":"#0","tintindex":0},"down":{"uv":[2.0,10.0,4.25,10.25],"rotation":0,"texture":"#0","tintindex":0}}},{"from":[7.643542,2.272788,7.973704],"to":[12.214972,9.70136,7.973704],"rotation":{"angle":0.0,"axis":"y","origin":[11.308807,5.987074,7.7370105]},"faces":{"east":{"uv":[4.25,10.5,4.25,13.75],"rotation":0,"texture":"#0","tintindex":0},"south":{"uv":[4.25,0.0,2.25,3.25],"rotation":0,"texture":"#0","tintindex":0},"north":{"uv":[2.25,0.0,4.25,3.25],"rotation":0,"texture":"#0","tintindex":0},"west":{"uv":[4.0,10.5,4.0,13.75],"rotation":0,"texture":"#0","tintindex":0},"up":{"uv":[10.5,4.5,12.5,4.5],"rotation":0,"texture":"#0","tintindex":0},"down":{"uv":[10.5,4.75,12.5,4.75],"rotation":0,"texture":"#0","tintindex":0}}}],"display":{"head":{"translation":[0.0,-6.4,0.0],"scale":[4.0,4.0,4.0]}}}